revoltutils/__init__.py
revoltutils/bannerutils.py
revoltutils/cacheutils.py
revoltutils/configutils.py
revoltutils/dnsutils.py
revoltutils/encodingutils.py
revoltutils/fileutils.py
revoltutils/folderutils.py
revoltutils/genericutils.py
revoltutils/healthcheckutils.py
revoltutils/httputils.py
revoltutils/iputils.py
revoltutils/osutils.py
revoltutils/permissionutils.py
revoltutils/progressbarutils.py
revoltutils/queueutils.py
revoltutils/randomutils.py
revoltutils/resourceutils.py
revoltutils/sysutils.py
revoltutils/tempdirutils.py
revoltutils/tempfileutils.py
revoltutils/urlutils.py
revoltutils/yamlutils.py
revoltutils-1.0.2.dist-info/licenses/LICENSE
revoltutils-1.0.2.dist-info/METADATA
revoltutils-1.0.2.dist-info/WHEEL
revoltutils-1.0.2.dist-info/entry_points.txt
revoltutils-1.0.2.dist-info/top_level.txt
revoltutils-1.0.2.dist-info/RECORD
