Metadata-Version: 2.4
Name: revoltutils
Version: 1.0.2
Summary: revoltutils is an Python utility library offering modular tools for networking, file operations, system info, and automation.
Author-email: "D. Sanjai Kumar" <bughunterz0047@gmail.com>
License: MIT
Project-URL: Homepage, https://github.com/RevoltSecurities/revoltutils
Project-URL: Documentation, https://github.com/RevoltSecurities/revoltutils
Project-URL: Source, https://github.com/RevoltSecurities/revoltutils
Project-URL: Issues, https://github.com/RevoltSecurities/revoltutils/issues
Keywords: revoltutils,python-utils,networking,system-tools,asyncio,pentesting,bugbounty,tooling,automation,cli
Classifier: Development Status :: 5 - Production/Stable
Classifier: Programming Language :: Python :: 3
Classifier: Programming Language :: Python :: 3.13
Classifier: License :: OSI Approved :: MIT License
Classifier: Operating System :: OS Independent
Classifier: Intended Audience :: Developers
Classifier: Topic :: Software Development :: Libraries :: Python Modules
Classifier: Topic :: Utilities
Classifier: Topic :: System :: Networking
Classifier: Topic :: System :: Logging
Requires-Python: >=3.13
License-File: LICENSE
Requires-Dist: aiodns>=3.5.0
Requires-Dist: aiofiles>=24.1.0
Requires-Dist: alive-progress>=3.2.0
Requires-Dist: appdirs>=1.4.4
Requires-Dist: art>=6.5
Requires-Dist: diskcache>=5.6.3
Requires-Dist: fake-useragent>=2.2.0
Requires-Dist: httpx>=0.28.1
Requires-Dist: psutil>=7.0.0
Requires-Dist: pyyaml>=6.0.2
Requires-Dist: requests>=2.32.4
Requires-Dist: revoltlogger>=1.0.0
Requires-Dist: tldextract>=5.3.0
Dynamic: license-file
